izihawa_netlib/__init__.py
izihawa_netlib/_client_pool.py
izihawa_netlib-0.1.2.dist-info/METADATA
izihawa_netlib-0.1.2.dist-info/WHEEL
izihawa_netlib-0.1.2.dist-info/RECORD
