Metadata-Version: 2.1
Name: izihawa_netlib
Version: 0.1.2
Summary: Izihawa network utilities
Author: Pasha Podolsky
Author-email: ppodolsky@me.com
Requires-Python: >=3.8,<4.0
Classifier: Programming Language :: Python :: 3
Classifier: Programming Language :: Python :: 3.8
Classifier: Programming Language :: Python :: 3.9
Classifier: Programming Language :: Python :: 3.10
Classifier: Programming Language :: Python :: 3.11
Classifier: Programming Language :: Python :: 3.12
